bird2glass/__init__.py
bird2glass/__main__.py
bird2glass/tweet.py
bird2glass-1.0.0.dist-info/METADATA
bird2glass-1.0.0.dist-info/WHEEL
bird2glass-1.0.0.dist-info/entry_points.txt
bird2glass-1.0.0.dist-info/licenses/LICENSE
bird2glass-1.0.0.dist-info/RECORD
