Metadata-Version: 2.3
Name: bird2glass
Version: 1.0.0
Summary: A tool for converting Twitter exports to an Obsidian Vault.
Project-URL: Homepage, https://github.com/davep/bird2glass
Project-URL: Repository, https://github.com/davep/bird2glass
Project-URL: Documentation, https://github.com/davep/bird2glass
Project-URL: Issues, https://github.com/davep/bird2glass/issues
Author-email: Dave Pearson <davep@davep.org>
License:                     GNU GENERAL PUBLIC LICENSE
License-File: LICENSE
Requires-Python: >=3.12
Requires-Dist: python-dateutil>=2.9.0.post0
